MANIFEST.in
README.md
requirements.pip
setup.cfg
setup.py
le_trebuchet.egg-info/PKG-INFO
le_trebuchet.egg-info/SOURCES.txt
le_trebuchet.egg-info/dependency_links.txt
le_trebuchet.egg-info/entry_points.txt
le_trebuchet.egg-info/requires.txt
le_trebuchet.egg-info/top_level.txt
trebuchet/__init__.py
trebuchet/__init__.pyc
trebuchet/parser.py
trebuchet/parser.pyc
trebuchet/run.py
trebuchet/lib/__init__.py
trebuchet/lib/__init__.pyc
trebuchet/lib/callbacks.py
trebuchet/lib/callbacks.pyc
trebuchet/lib/controller.py
trebuchet/lib/controller.pyc
trebuchet/lib/custom_file.py
trebuchet/lib/custom_file.pyc
trebuchet/lib/logger.py
trebuchet/lib/my_yaml.py
trebuchet/lib/my_yaml.pyc
trebuchet/lib/package.py
trebuchet/lib/package.pyc
trebuchet/lib/utils.py
trebuchet/lib/utils.pyc
trebuchet/templates/base_shell.sh
trebuchet/templates/config.ini
trebuchet/templates/DEBIAN/control
trebuchet/templates/DEBIAN/postinst
trebuchet/templates/DEBIAN/preinst
trebuchet/templates/DEBIAN/prerm
trebuchet/templates/upstart/base-service.conf
trebuchet/templates/upstart/controller.conf