Metadata-Version: 1.1
Name: le-trebuchet
Version: 0.0.9
Summary: Yet another package building tool
Home-page: https://github.com/ops-hero/trebuchet
Author: Arnaud Seilles
Author-email: arnaud.seilles@gmail.com
License: UNKNOWN
Platform: UNKNOWN
Classifier: Development Status :: 3 - Alpha
Classifier: Intended Audience :: Information Technology
Classifier: License :: OSI Approved :: GNU Affero General Public License v3
Classifier: Operating System :: POSIX :: Linux
Classifier: Programming Language :: Python :: 2.7
Classifier: Topic :: Software Development :: Build Tools
